[
  {
    "team": "Argentina",
    "win_pct": 28.5
  },
  {
    "team": "Colombia",
    "win_pct": 14.1
  },
  {
    "team": "France",
    "win_pct": 14.0
  },
  {
    "team": "Spain",
    "win_pct": 12.2
  },
  {
    "team": "England",
    "win_pct": 6.9
  },
  {
    "team": "Brazil",
    "win_pct": 6.9
  },
  {
    "team": "Croatia",
    "win_pct": 3.9
  },
  {
    "team": "Morocco",
    "win_pct": 3.9
  },
  {
    "team": "Portugal",
    "win_pct": 3.1
  },
  {
    "team": "Switzerland",
    "win_pct": 1.3
  },
  {
    "team": "Algeria",
    "win_pct": 1.2
  },
  {
    "team": "Belgium",
    "win_pct": 0.9
  },
  {
    "team": "Ecuador",
    "win_pct": 0.8
  },
  {
    "team": "Mexico",
    "win_pct": 0.5
  },
  {
    "team": "United States",
    "win_pct": 0.4
  },
  {
    "team": "Egypt",
    "win_pct": 0.4
  },
  {
    "team": "Sweden",
    "win_pct": 0.3
  },
  {
    "team": "Australia",
    "win_pct": 0.2
  },
  {
    "team": "Senegal",
    "win_pct": 0.2
  },
  {
    "team": "Ivory Coast",
    "win_pct": 0.1
  },
  {
    "team": "Norway",
    "win_pct": 0.1
  },
  {
    "team": "Paraguay",
    "win_pct": 0.1
  }
]